RSree/Ml.py
RSree/RunNs.py
RSree/__init__.py
RSree-0.0.2.dist-info/METADATA
RSree-0.0.2.dist-info/WHEEL
RSree-0.0.2.dist-info/top_level.txt
RSree-0.0.2.dist-info/RECORD
